notebridge/__init__.py
notebridge/bridge.py
notebridge/executor.py
notebridge/hello_page.py
notebridge-0.5.4.dist-info/WHEEL
notebridge-0.5.4.dist-info/METADATA
notebridge-0.5.4.dist-info/RECORD
