Metadata-Version: 2.1
Name: notebridge
Version: 0.5.4
Summary: Notebridge is a tool to connect NoteAid app to your user-defined agent.
Home-page: https://notebridge.lingxi.li/
License: MIT
Author: Lingxi Li
Author-email: hi@lingxi.li
Requires-Python: >=3.8,<4
Classifier: License :: OSI Approved :: MIT License
Classifier: Programming Language :: Python :: 3
Classifier: Programming Language :: Python :: 3.8
Classifier: Programming Language :: Python :: 3.9
Classifier: Programming Language :: Python :: 3.10
Classifier: Programming Language :: Python :: 3.11
Requires-Dist: flask (>=3.0.0,<4.0.0)
Requires-Dist: pydantic (>=2.2.1,<3.0.0)
Requires-Dist: requests (>=2.31.0,<3.0.0)
Project-URL: Repository, https://github.com/lilingxi01/notebridge
